LICENSE
MANIFEST.in
README.txt
pybtctool
setup.py
bitcoin/__init__.py
bitcoin/bci.py
bitcoin/blocks.py
bitcoin/composite.py
bitcoin/deterministic.py
bitcoin/main.py
bitcoin/mnemonic.py
bitcoin/py2specials.py
bitcoin/py3specials.py
bitcoin/ripemd.py
bitcoin/stealth.py
bitcoin/transaction.py
bitcoin.egg-info/PKG-INFO
bitcoin.egg-info/SOURCES.txt
bitcoin.egg-info/dependency_links.txt
bitcoin.egg-info/top_level.txt