Metadata-Version: 1.0
Name: bitcoin
Version: 1.1.40
Summary: Python Bitcoin Tools
Home-page: http://github.com/vbuterin/pybitcointools
Author: Vitalik Buterin
Author-email: vbuterin@gmail.com
License: UNKNOWN
Platform: UNKNOWN
